COPYING
LICENSE
MANIFEST.in
README.rst
setup.py
django_mongo_auth.egg-info/PKG-INFO
django_mongo_auth.egg-info/SOURCES.txt
django_mongo_auth.egg-info/dependency_links.txt
django_mongo_auth.egg-info/not-zip-safe
django_mongo_auth.egg-info/requires.txt
django_mongo_auth.egg-info/top_level.txt
docs/Makefile
docs/conf.py
docs/index.rst
docs/installation.rst
mongo_auth/__init__.py
mongo_auth/backends.py
mongo_auth/forms.py
mongo_auth/middleware.py
mongo_auth/models.py
mongo_auth/urls.py
mongo_auth/utils.py
mongo_auth/views.py
mongo_auth/contrib/__init__.py
mongo_auth/contrib/context_processors.py
mongo_auth/contrib/fields.py
mongo_auth/contrib/form_fields.py
mongo_auth/contrib/forms.py
mongo_auth/contrib/middleware.py
mongo_auth/contrib/models.py
mongo_auth/contrib/urls.py
mongo_auth/contrib/views.py
mongo_auth/contrib/static/mongo_auth/js/browserid_login.js
mongo_auth/contrib/templates/mongo_auth/account.html
mongo_auth/contrib/templates/mongo_auth/base.html
mongo_auth/contrib/templates/mongo_auth/browserid.html
mongo_auth/contrib/templates/mongo_auth/confirmation_email.txt
mongo_auth/contrib/templates/mongo_auth/confirmation_email_subject.txt
mongo_auth/contrib/templates/mongo_auth/email_confirmation_process_token.html
mongo_auth/contrib/templates/mongo_auth/email_confirmation_send_token.html
mongo_auth/contrib/templates/mongo_auth/form.html
mongo_auth/contrib/templates/mongo_auth/login.html
mongo_auth/contrib/templates/mongo_auth/other_login_options.html
mongo_auth/contrib/templates/mongo_auth/password_change.html
mongo_auth/contrib/templates/mongo_auth/password_reset_confirm.html
mongo_auth/contrib/templates/mongo_auth/password_reset_email.txt
mongo_auth/contrib/templates/mongo_auth/password_reset_form.html
mongo_auth/contrib/templates/mongo_auth/password_reset_subject.txt
mongo_auth/contrib/templates/mongo_auth/registration.html
mongo_auth/contrib/templates/mongo_auth/user_image.html
mongo_auth/contrib/templates/mongo_auth/base/account.html
mongo_auth/contrib/templates/mongo_auth/base/email_confirmation_process_token.html
mongo_auth/contrib/templates/mongo_auth/base/email_confirmation_send_token.html
mongo_auth/contrib/templates/mongo_auth/base/login.html
