Metadata-Version: 1.0
Name: django-mongo-auth
Version: 0.1.2
Summary: Django authentication based on an extensible MongoEngine user class.
Home-page: https://github.com/mitar/django-mongo-auth
Author: Mitar
Author-email: mitar.django@tnode.com
License: AGPLv3
Platform: UNKNOWN
Classifier: Development Status :: 4 - Beta
Classifier: Environment :: Web Environment
Classifier: Intended Audience :: Developers
Classifier: License :: OSI Approved :: GNU Affero General Public License v3
Classifier: Operating System :: OS Independent
Classifier: Programming Language :: Python
Classifier: Framework :: Django
